{"ID":"PVT_kwHOBZSipc4AuISm","IssuesDict":{"1":"PVTI_lAHOBZSipc4AuISmzgVrKp8","5":"PVTI_lAHOBZSipc4AuISmzgVltkE","6":"PVTI_lAHOBZSipc4AuISmzgVrKpU"},"FieldsDict":{"":"","Assignees":"PVTF_lAHOBZSipc4AuISmzgkxrhw","Labels":"PVTF_lAHOBZSipc4AuISmzgkxrh4","Linked pull requests":"PVTF_lAHOBZSipc4AuISmzgkxrh8","Milestone":"PVTF_lAHOBZSipc4AuISmzgkxriA","Repository":"PVTF_lAHOBZSipc4AuISmzgkxriE","Reviewers":"PVTF_lAHOBZSipc4AuISmzgkxriQ","Title":"PVTF_lAHOBZSipc4AuISmzgkxrhs","kijitu":"PVTF_lAHOBZSipc4AuISmzgkxryw","traQID":"PVTF_lAHOBZSipc4AuISmzglHHos"}}